{
  "Persons": [
    {
      "Fio": "asfafasf",
      "Address": "asfasfasfasf",
      "Phone": "asfasfasfas",
      "DependencyObjectType": {
        "Id": 109,
        "SystemType": "Notebook.PersonModel, Notebook, Version=1.0.0.0, Culture=neutral, PublicKeyToken=null",
        "BaseType": {
          "Id": 0,
          "SystemType": "System.Windows.DependencyObject, WindowsBase, Version=7.0.0.0, Culture=neutral, PublicKeyToken=31bf3856ad364e35",
          "BaseType": null,
          "Name": "DependencyObject"
        },
        "Name": "PersonModel"
      },
      "IsSealed": false,
      "Dispatcher": {
        "Thread": {
          "ManagedThreadId": 1,
          "IsAlive": true,
          "IsBackground": false,
          "IsThreadPoolThread": false,
          "Priority": 2,
          "ThreadState": 0,
          "CurrentCulture": "ru-RU",
          "CurrentUICulture": "ru-RU",
          "ExecutionContext": {},
          "Name": null,
          "ApartmentState": 0
        },
        "HasShutdownStarted": false,
        "HasShutdownFinished": false,
        "Hooks": {}
      }
    },
    {
      "Fio": "safasfa",
      "Address": "asfasf",
      "Phone": "asfasdf",
      "DependencyObjectType": {
        "Id": 109,
        "SystemType": "Notebook.PersonModel, Notebook, Version=1.0.0.0, Culture=neutral, PublicKeyToken=null",
        "BaseType": {
          "Id": 0,
          "SystemType": "System.Windows.DependencyObject, WindowsBase, Version=7.0.0.0, Culture=neutral, PublicKeyToken=31bf3856ad364e35",
          "BaseType": null,
          "Name": "DependencyObject"
        },
        "Name": "PersonModel"
      },
      "IsSealed": false,
      "Dispatcher": {
        "Thread": {
          "ManagedThreadId": 1,
          "IsAlive": true,
          "IsBackground": false,
          "IsThreadPoolThread": false,
          "Priority": 2,
          "ThreadState": 0,
          "CurrentCulture": "ru-RU",
          "CurrentUICulture": "ru-RU",
          "ExecutionContext": {},
          "Name": null,
          "ApartmentState": 0
        },
        "HasShutdownStarted": false,
        "HasShutdownFinished": false,
        "Hooks": {}
      }
    }
  ]
}